MANIFEST.in
requirements.txt
setup.py
luigi_td/__init__.py
luigi_td/bulk_import.py
luigi_td/client.py
luigi_td/config.py
luigi_td/task.py
luigi_td/test_bulk_import.py
luigi_td/test_client.py
luigi_td/test_config.py
luigi_td/test_helper.py
luigi_td/test_task.py
luigi_td.egg-info/PKG-INFO
luigi_td.egg-info/SOURCES.txt
luigi_td.egg-info/dependency_links.txt
luigi_td.egg-info/pbr.json
luigi_td.egg-info/requires.txt
luigi_td.egg-info/top_level.txt
luigi_td/targets/__init__.py
luigi_td/targets/result.py
luigi_td/targets/s3.py
luigi_td/targets/tableau.py
luigi_td/targets/td.py
luigi_td/targets/test_result.py
luigi_td/targets/test_s3.py
luigi_td/targets/test_tableau.py
luigi_td/targets/test_td.py